{
   "abstract" : "Manage a module's machine-readable Changes/CHANGES file",
   "author" : [
      "Ron Savage (ron@savage.net.au)"
   ],
   "dynamic_config" : 0,
   "generated_by" : "ExtUtils::MakeMaker version 7.06, CPAN::Meta::Converter version 2.143240",
   "license" : [
      "artistic_2"
   ],
   "meta-spec" : {
      "url" : "http://search.cpan.org/perldoc?CPAN::Meta::Spec",
      "version" : "2"
   },
   "name" : "Module-Metadata-Changes",
   "no_index" : {
      "directory" : [
         "t",
         "inc"
      ]
   },
   "prereqs" : {
      "build" : {
         "requires" : {
            "ExtUtils::MakeMaker" : "0"
         }
      },
      "configure" : {
         "requires" : {
            "ExtUtils::MakeMaker" : "0"
         }
      },
      "runtime" : {
         "requires" : {
            "Config::IniFiles" : "2.88",
            "DateTime" : "0.66",
            "DateTime::Format::HTTP" : "0.42",
            "DateTime::Format::Strptime" : "1.61",
            "DateTime::Format::W3CDTF" : "0.06",
            "File::Slurper" : "0.008",
            "HTML::Entities::Interpolate" : "1.06",
            "HTML::Template" : "2.95",
            "Moo" : "2.000002",
            "Test::Pod" : "1.48",
            "Test::Stream" : "1.302026",
            "Type::Tiny" : "1.000005",
            "version" : "0"
         }
      }
   },
   "release_status" : "stable",
   "version" : "2.06"
}
